AioKafkaEngine/ConsumerEngine.py
AioKafkaEngine/ProducerEngine.py
AioKafkaEngine/__init__.py
aiokafkaengine-0.1.0.dist-info/METADATA
aiokafkaengine-0.1.0.dist-info/WHEEL
aiokafkaengine-0.1.0.dist-info/licenses/LICENSE
aiokafkaengine-0.1.0.dist-info/RECORD
