Metadata-Version: 2.3
Name: AioKafkaEngine
Version: 0.1.0
Summary: Wrapper around aio-kafka to use and receive via a asyncio queue
Project-URL: Homepage, https://github.com/Bot-detector/AioKafkaEngine
Project-URL: Bug Tracker, https://github.com/Bot-detector/AioKafkaEngine/issues
Author-email: Extreme4all <author@example.com>
Classifier: License :: OSI Approved :: MIT License
Classifier: Operating System :: OS Independent
Classifier: Programming Language :: Python :: 3
Requires-Python: >=3.9
Requires-Dist: aiokafka>=0.12.0
Requires-Dist: asyncio>=3.4.3
